thumbor_greenthumb_filter/__init__.py
thumbor_greenthumb_filter/bud_area.py
thumbor_greenthumb_filter/leaf_area.py
thumbor_greenthumb_filter-0.0.7.dist-info/METADATA
thumbor_greenthumb_filter-0.0.7.dist-info/WHEEL
thumbor_greenthumb_filter-0.0.7.dist-info/top_level.txt
thumbor_greenthumb_filter-0.0.7.dist-info/RECORD
