Metadata-Version: 2.1
Name: thumbor-greenthumb-filter
Version: 0.0.7
Summary: GreenThumb CV
Home-page: UNKNOWN
Author: GreenThumb.io
Author-email: justin@greenthumb.io
License: UNKNOWN
Keywords: thumbor filter
Platform: UNKNOWN
Classifier: Development Status :: 4 - Beta
Classifier: Intended Audience :: Developers
Classifier: Natural Language :: English
Classifier: Operating System :: MacOS
Classifier: Operating System :: POSIX
Classifier: Operating System :: Unix
Classifier: Operating System :: OS Independent
Classifier: Programming Language :: Python :: 2.7
Requires-Dist: pillow
Provides-Extra: tests
Requires-Dist: mock ; extra == 'tests'
Requires-Dist: nose ; extra == 'tests'
Requires-Dist: coverage ; extra == 'tests'
Requires-Dist: yanc ; extra == 'tests'
Requires-Dist: colorama ; extra == 'tests'
Requires-Dist: preggy ; extra == 'tests'
Requires-Dist: ipdb ; extra == 'tests'
Requires-Dist: coveralls ; extra == 'tests'
Requires-Dist: numpy ; extra == 'tests'
